LICENSE
README.md
setup.cfg
setup.py
pytwex/__init__.py
pytwex/base_exceptions.py
pytwex/client.py
pytwex/create_tweet.py
pytwex/follow.py
pytwex/get_media_id.py
pytwex/get_tweet_details.py
pytwex/like_tweet.py
pytwex/pin_tweet.py
pytwex/reply.py
pytwex/retweet.py
pytwex/setup.py
pytwex/utils.py
pytwex.egg-info/PKG-INFO
pytwex.egg-info/SOURCES.txt
pytwex.egg-info/dependency_links.txt
pytwex.egg-info/requires.txt
pytwex.egg-info/top_level.txt