Metadata-Version: 2.1
Name: pytwex
Version: 0.1.6
Summary: Python asynchronous module for interacting with Twitter using auth_token for Python 3.10+
Author: flexter1
License-File: LICENSE
